diracx/cli/__init__.py
diracx/cli/__main__.py
diracx/cli/auth.py
diracx/cli/config.py
diracx/cli/jobs.py
diracx/cli/py.typed
diracx/cli/utils.py
diracx/cli/internal/__init__.py
diracx/cli/internal/config.py
diracx/cli/internal/legacy.py
diracx_cli-0.0.7.dist-info/METADATA
diracx_cli-0.0.7.dist-info/WHEEL
diracx_cli-0.0.7.dist-info/entry_points.txt
diracx_cli-0.0.7.dist-info/RECORD
